{
"meta":{"test_sets":[],"test_metrics":[],"learn_metrics":[{"best_value":"Min","name":"Logloss"}],"launch_mode":"Train","parameters":"","iteration_count":331,"learn_sets":["learn"],"name":"experiment"},
"iterations":[
{"learn":[0.6903815703],"iteration":0,"passed_time":0.004987306289,"remaining_time":1.645811075},
{"learn":[0.6868181229],"iteration":1,"passed_time":0.0099015722,"remaining_time":1.628808627},
{"learn":[0.6836616343],"iteration":2,"passed_time":0.01481525512,"remaining_time":1.619801227},
{"learn":[0.6811699434],"iteration":3,"passed_time":0.01981176921,"remaining_time":1.619612133},
{"learn":[0.6780502146],"iteration":4,"passed_time":0.02495678,"remaining_time":1.627182056},
{"learn":[0.6750378609],"iteration":5,"passed_time":0.03004966694,"remaining_time":1.627690293},
{"learn":[0.6715761531],"iteration":6,"passed_time":0.03508668013,"remaining_time":1.624012052},
{"learn":[0.6677783186],"iteration":7,"passed_time":0.03985915718,"remaining_time":1.609313471},
{"learn":[0.6650604768],"iteration":8,"passed_time":0.04467659224,"remaining_time":1.598429189},
{"learn":[0.6618156433],"iteration":9,"passed_time":0.04962769034,"remaining_time":1.59304886},
{"learn":[0.6572192799],"iteration":10,"passed_time":0.05463191225,"remaining_time":1.589291993},
{"learn":[0.6533286355],"iteration":11,"passed_time":0.05976900722,"remaining_time":1.588859442},
{"learn":[0.6500055573],"iteration":12,"passed_time":0.064688773,"remaining_time":1.582386909},
{"learn":[0.6464140198],"iteration":13,"passed_time":0.06957408156,"remaining_time":1.57535599},
{"learn":[0.6430897713],"iteration":14,"passed_time":0.07435301747,"remaining_time":1.566370235},
{"learn":[0.640046033],"iteration":15,"passed_time":0.07960394291,"remaining_time":1.567202626},
{"learn":[0.6364694075],"iteration":16,"passed_time":0.08444758539,"remaining_time":1.559796577},
{"learn":[0.6328025298],"iteration":17,"passed_time":0.08963488724,"remaining_time":1.558651095},
{"learn":[0.630414616],"iteration":18,"passed_time":0.09496981081,"remaining_time":1.559504262},
{"learn":[0.6269769235],"iteration":19,"passed_time":0.09982478604,"remaining_time":1.552275423},
{"learn":[0.624337023],"iteration":20,"passed_time":0.1053726209,"remaining_time":1.555500594},
{"learn":[0.6218687838],"iteration":21,"passed_time":0.1106615455,"remaining_time":1.554291707},
{"learn":[0.6175844886],"iteration":22,"passed_time":0.1154826885,"remaining_time":1.546463828},
{"learn":[0.6145213301],"iteration":23,"passed_time":0.1204377875,"remaining_time":1.540600031},
{"learn":[0.6121324626],"iteration":24,"passed_time":0.1254333436,"remaining_time":1.535304125},
{"learn":[0.6091291254],"iteration":25,"passed_time":0.1305541459,"remaining_time":1.531500558},
{"learn":[0.6058885401],"iteration":26,"passed_time":0.1356297832,"remaining_time":1.527090893},
{"learn":[0.6030025049],"iteration":27,"passed_time":0.1406197564,"remaining_time":1.52170665},
{"learn":[0.600371144],"iteration":28,"passed_time":0.1456304782,"remaining_time":1.51656567},
{"learn":[0.5979754275],"iteration":29,"passed_time":0.1503943725,"remaining_time":1.50895687},
{"learn":[0.5934999639],"iteration":30,"passed_time":0.1515085147,"remaining_time":1.466211433},
{"learn":[0.5908165412],"iteration":31,"passed_time":0.1563020333,"remaining_time":1.460447124},
{"learn":[0.5878838626],"iteration":32,"passed_time":0.1614030451,"remaining_time":1.457518407},
{"learn":[0.5853219899],"iteration":33,"passed_time":0.16627427,"remaining_time":1.452454652},
{"learn":[0.5824026628],"iteration":34,"passed_time":0.1709885403,"remaining_time":1.446074512},
{"learn":[0.5795503963],"iteration":35,"passed_time":0.1758075583,"remaining_time":1.44064527},
{"learn":[0.5775071057],"iteration":36,"passed_time":0.1808169471,"remaining_time":1.436761688},
{"learn":[0.5746852268],"iteration":37,"passed_time":0.1860692885,"remaining_time":1.434692146},
{"learn":[0.5726883628],"iteration":38,"passed_time":0.1911690503,"remaining_time":1.431316992},
{"learn":[0.5702853636],"iteration":39,"passed_time":0.1963592681,"remaining_time":1.428513676},
{"learn":[0.5681132837],"iteration":40,"passed_time":0.2015977358,"remaining_time":1.425935205},
{"learn":[0.5658095533],"iteration":41,"passed_time":0.2069873242,"remaining_time":1.424269921},
{"learn":[0.5636981617],"iteration":42,"passed_time":0.2117936765,"remaining_time":1.418525089},
{"learn":[0.5615328875],"iteration":43,"passed_time":0.2167853577,"remaining_time":1.414031765},
{"learn":[0.559258461],"iteration":44,"passed_time":0.2218897444,"remaining_time":1.410232598},
{"learn":[0.5565664551],"iteration":45,"passed_time":0.2267065124,"remaining_time":1.404594697},
{"learn":[0.5533217517],"iteration":46,"passed_time":0.2292966219,"remaining_time":1.385537035},
{"learn":[0.5506606969],"iteration":47,"passed_time":0.2343003439,"remaining_time":1.381395777},
{"learn":[0.5484993675],"iteration":48,"passed_time":0.2393136076,"remaining_time":1.377274231},
{"learn":[0.5460223285],"iteration":49,"passed_time":0.2443263293,"remaining_time":1.373113971},
{"learn":[0.5432924791],"iteration":50,"passed_time":0.2461494558,"remaining_time":1.351408777},
{"learn":[0.5411642248],"iteration":51,"passed_time":0.2518723698,"remaining_time":1.351392138},
{"learn":[0.5390823538],"iteration":52,"passed_time":0.2567831778,"remaining_time":1.346900442},
{"learn":[0.536017678],"iteration":53,"passed_time":0.2617681501,"remaining_time":1.342773659},
{"learn":[0.5334575826],"iteration":54,"passed_time":0.2667265811,"remaining_time":1.338482479},
{"learn":[0.5306891528],"iteration":55,"passed_time":0.2718397176,"remaining_time":1.334927184},
{"learn":[0.5285602916],"iteration":56,"passed_time":0.2769917282,"remaining_time":1.331504097},
{"learn":[0.5262690891],"iteration":57,"passed_time":0.282090407,"remaining_time":1.327770364},
{"learn":[0.52446296],"iteration":58,"passed_time":0.2871619194,"remaining_time":1.32386512},
{"learn":[0.5225878629],"iteration":59,"passed_time":0.2919586459,"remaining_time":1.318679884},
{"learn":[0.5194013769],"iteration":60,"passed_time":0.2970750744,"remaining_time":1.31492246},
{"learn":[0.5169194828],"iteration":61,"passed_time":0.3022615842,"remaining_time":1.311425261},
{"learn":[0.5146455765],"iteration":62,"passed_time":0.3071621834,"remaining_time":1.306658177},
{"learn":[0.5123369044],"iteration":63,"passed_time":0.3119050362,"remaining_time":1.301228823},
{"learn":[0.5104917613],"iteration":64,"passed_time":0.3169813395,"remaining_time":1.297185174},
{"learn":[0.5088290301],"iteration":65,"passed_time":0.3226374219,"remaining_time":1.295438133},
{"learn":[0.5065308918],"iteration":66,"passed_time":0.3276167284,"remaining_time":1.290907706},
{"learn":[0.5041913553],"iteration":67,"passed_time":0.3326852819,"remaining_time":1.286709252},
{"learn":[0.5019594539],"iteration":68,"passed_time":0.3354952615,"remaining_time":1.273909544},
{"learn":[0.5000143485],"iteration":69,"passed_time":0.3402836972,"remaining_time":1.268772071},
{"learn":[0.4974855943],"iteration":70,"passed_time":0.345202921,"remaining_time":1.264123373},
{"learn":[0.4958770058],"iteration":71,"passed_time":0.3502548089,"remaining_time":1.259944382},
{"learn":[0.49406134],"iteration":72,"passed_time":0.3550113283,"remaining_time":1.254697571},
{"learn":[0.4923606352],"iteration":73,"passed_time":0.3599505516,"remaining_time":1.250098537},
{"learn":[0.4903059873],"iteration":74,"passed_time":0.3648319433,"remaining_time":1.245293033},
{"learn":[0.4877736352],"iteration":75,"passed_time":0.3696257118,"remaining_time":1.240191533},
{"learn":[0.4849851782],"iteration":76,"passed_time":0.3742563591,"remaining_time":1.234559938},
{"learn":[0.4829896147],"iteration":77,"passed_time":0.3790476277,"remaining_time":1.229474998},
{"learn":[0.4806450931],"iteration":78,"passed_time":0.3837228579,"remaining_time":1.224027344},
{"learn":[0.4789212834],"iteration":79,"passed_time":0.3886990804,"remaining_time":1.219543365},
{"learn":[0.4765588587],"iteration":80,"passed_time":0.3935442649,"remaining_time":1.214642793},
{"learn":[0.4740806059],"iteration":81,"passed_time":0.3952639767,"remaining_time":1.200252807},
{"learn":[0.4718338359],"iteration":82,"passed_time":0.3980361652,"remaining_time":1.189312879},
{"learn":[0.4698330706],"iteration":83,"passed_time":0.4025367743,"remaining_time":1.183649801},
{"learn":[0.4677883495],"iteration":84,"passed_time":0.407281128,"remaining_time":1.1787195},
{"learn":[0.4656255028],"iteration":85,"passed_time":0.4123417656,"remaining_time":1.174694565},
{"learn":[0.4639352452],"iteration":86,"passed_time":0.4174075702,"remaining_time":1.170660312},
{"learn":[0.4620448893],"iteration":87,"passed_time":0.4224410004,"remaining_time":1.166513217},
{"learn":[0.4601471641],"iteration":88,"passed_time":0.4273453916,"remaining_time":1.161995334},
{"learn":[0.4584760666],"iteration":89,"passed_time":0.4324715688,"remaining_time":1.158062756},
{"learn":[0.4565431855],"iteration":90,"passed_time":0.4374677909,"remaining_time":1.153761207},
{"learn":[0.4547188499],"iteration":91,"passed_time":0.4423495995,"remaining_time":1.149147329},
{"learn":[0.4529388601],"iteration":92,"passed_time":0.4474109451,"remaining_time":1.14498715},
{"learn":[0.4513194344],"iteration":93,"passed_time":0.4524367496,"remaining_time":1.140718188},
{"learn":[0.4497906945],"iteration":94,"passed_time":0.4577751731,"remaining_time":1.137209904},
{"learn":[0.4480705261],"iteration":95,"passed_time":0.4628968504,"remaining_time":1.133132915},
{"learn":[0.4466315183],"iteration":96,"passed_time":0.4680594028,"remaining_time":1.129132992},
{"learn":[0.4446820346],"iteration":97,"passed_time":0.4731710393,"remaining_time":1.124988287},
{"learn":[0.4426822229],"iteration":98,"passed_time":0.4784712136,"remaining_time":1.121265874},
{"learn":[0.4405441284],"iteration":99,"passed_time":0.4839293425,"remaining_time":1.117876781},
{"learn":[0.4387880672],"iteration":100,"passed_time":0.4889704806,"remaining_time":1.113497134},
{"learn":[0.4373572956],"iteration":101,"passed_time":0.4938552471,"remaining_time":1.108753447},
{"learn":[0.4359537905],"iteration":102,"passed_time":0.4986108076,"remaining_time":1.103721011},
{"learn":[0.4339634288],"iteration":103,"passed_time":0.5038240258,"remaining_time":1.099692826},
{"learn":[0.4320910194],"iteration":104,"passed_time":0.5089694116,"remaining_time":1.095496067},
{"learn":[0.430608706],"iteration":105,"passed_time":0.5139218017,"remaining_time":1.090871749},
{"learn":[0.4290593754],"iteration":106,"passed_time":0.518726445,"remaining_time":1.085931997},
{"learn":[0.4274741953],"iteration":107,"passed_time":0.523819582,"remaining_time":1.081590433},
{"learn":[0.4258609685],"iteration":108,"passed_time":0.5286561406,"remaining_time":1.076712507},
{"learn":[0.4243888855],"iteration":109,"passed_time":0.5333851186,"remaining_time":1.071619193},
{"learn":[0.4225562703],"iteration":110,"passed_time":0.5354544887,"remaining_time":1.061261149},
{"learn":[0.4202340733],"iteration":111,"passed_time":0.540532001,"remaining_time":1.056933109},
{"learn":[0.4188973253],"iteration":112,"passed_time":0.545711303,"remaining_time":1.052788177},
{"learn":[0.4173977158],"iteration":113,"passed_time":0.5507235257,"remaining_time":1.048307062},
{"learn":[0.4156265259],"iteration":114,"passed_time":0.5559079937,"remaining_time":1.044140232},
{"learn":[0.4142361121],"iteration":115,"passed_time":0.5610995454,"remaining_time":1.039968985},
{"learn":[0.4125657515],"iteration":116,"passed_time":0.5661116431,"remaining_time":1.035452065},
{"learn":[0.4107864553],"iteration":117,"passed_time":0.5708847872,"remaining_time":1.030495421},
{"learn":[0.4093456268],"iteration":118,"passed_time":0.5758201356,"remaining_time":1.02583083},
{"learn":[0.4074705297],"iteration":119,"passed_time":0.5838802067,"remaining_time":1.02665603},
{"learn":[0.4061780409],"iteration":120,"passed_time":0.5889530941,"remaining_time":1.022149998}
]}